mosquittoChat/__init__.py
mosquittoChat/server.py
mosquittoChat/settings.py
mosquittoChat/urls.py
mosquittoChat/utils.py
mosquittoChat/apps/__init__.py
mosquittoChat/apps/main/__init__.py
mosquittoChat/apps/main/urls.py
mosquittoChat/apps/main/views.py
mosquittoChat/apps/mosquitto/__init__.py
mosquittoChat/apps/mosquitto/pubsub.py
mosquittoChat/static/css/style.css
mosquittoChat/static/js/date.js
mosquittoChat/static/js/script.js
mosquittoChat/templates/index.html
mosquittoChat-1.0.1.dist-info/DESCRIPTION.rst
mosquittoChat-1.0.1.dist-info/METADATA
mosquittoChat-1.0.1.dist-info/RECORD
mosquittoChat-1.0.1.dist-info/WHEEL
mosquittoChat-1.0.1.dist-info/entry_points.txt
mosquittoChat-1.0.1.dist-info/metadata.json
mosquittoChat-1.0.1.dist-info/top_level.txt
