Metadata-Version: 2.0
Name: mosquittoChat
Version: 1.0.1
Summary: A Chat Server based on MQTT protocol using Mosquitto (broker a C implementation of MQTT),                websocket, sockjs javascript library on client(browser) side, sockjs-tornado, tornado,                and paho-mqtt (mqtt python client library)
Home-page: https://github.com/anirbanroydas/mosquittoChat
Author: Anirban Roy Das
Author-email: anirban.nick@gmail.com
License: MIT
Keywords: chat server amqp protocol rabbitmq message broker via sockjs websocket tornado with sockjs-tornado and amqp python client library Pika
Platform: UNKNOWN
Classifier: Development Status :: 4 - Beta
Classifier: Intended Audience :: Developers
Classifier: License :: OSI Approved :: MIT License
Classifier: Natural Language :: English
Classifier: Operating System :: OS Independent
Classifier: Programming Language :: Python
Classifier: Programming Language :: Python :: 2
Classifier: Programming Language :: Python :: 2.7
Classifier: Programming Language :: Python :: Implementation :: CPython
Requires-Dist: paho-mqtt
Requires-Dist: setuptools (>=0.7.0)
Requires-Dist: sockjs-tornado
Requires-Dist: tornado (>=2.2.1)
